powerline_cpu_temp.py
powerline_cpu_temp-0.1.0.dist-info/LICENSE
powerline_cpu_temp-0.1.0.dist-info/METADATA
powerline_cpu_temp-0.1.0.dist-info/WHEEL
powerline_cpu_temp-0.1.0.dist-info/top_level.txt
powerline_cpu_temp-0.1.0.dist-info/RECORD
