Metadata-Version: 2.1
Name: powerline-cpu-temp
Version: 0.1.0
Summary: A Powerline segment to show CPU temperature
Home-page: https://github.com/DCsunset/powerline-cpu-temp
Author: DCsunset
Author-email: DCsunset@protonmail.com
License: MIT
Platform: UNKNOWN
Classifier: Environment :: Console
Classifier: Programming Language :: Python :: 3
Classifier: License :: OSI Approved :: MIT License
Classifier: Topic :: Terminals
Requires-Dist: psutil
